myToshokan/__init__.py
myToshokan/api.py
myToshokan/json.py
myToshokan/others.py
myToshokan/token.py
myToshokan-1.0.2.dist-info/METADATA
myToshokan-1.0.2.dist-info/WHEEL
myToshokan-1.0.2.dist-info/top_level.txt
myToshokan-1.0.2.dist-info/RECORD
