Metadata-Version: 2.1
Name: myToshokan
Version: 1.0.2
Summary: My library is your library.
Author: Robin Messiaen
Author-email: robin_messiaen@hotmail.fr
Classifier: Programming Language :: Python :: 3
Classifier: License :: OSI Approved :: MIT License
Classifier: Operating System :: OS Independent
Requires-Python: >=3.6
Requires-Dist: requests
